endra/__init__.py
endra/endra_api_brenthy_api.py
endra/endra_model.py
endra/exceptions.py
endra/log.py
endra/message/__init__.py
endra/message/message.py
endra/message/message_content.py
endra/message/message_encoding.py
endra/message/message_encoding_versions/__init__.py
endra/message/message_encoding_versions/attachment_encoding_v1.py
endra/message/message_encoding_versions/message_encoding_utils.py
endra/message/message_encoding_versions/message_encoding_v1.py
endra/message/message_encoding_versions/message_v1_pb2.py
endra-0.6.5.dist-info/licenses/LICENSE
endra-0.6.5.dist-info/licenses/LICENSE-CC0
endra-0.6.5.dist-info/METADATA
endra-0.6.5.dist-info/WHEEL
endra-0.6.5.dist-info/top_level.txt
endra-0.6.5.dist-info/RECORD
