Metadata-Version: 2.4
Name: endra
Version: 0.6.5
Summary: A fully distributed, no-servers, peer-to-peer encrypted messaging protocol.
Author: emendir
License-File: LICENSE
License-File: LICENSE-CC0
Requires-Dist: appdirs==1.4.4
Requires-Dist: protobuf
Requires-Dist: dataclasses-json
Requires-Dist: walytis_identities<0.6.0,>=0.5.0
Requires-Dist: walytis-mutability==0.1.7
Requires-Dist: walytis-offchain<0.6.0,>=0.5.1
Requires-Dist: codec-versioning
Dynamic: license-file
